<?xml version="1.0" encoding="UTF-8"?>
<!DOCTYPE mapper PUBLIC "-//mybatis.org//DTD Mapper 3.0//EN" "http://mybatis.org/dtd/mybatis-3-mapper.dtd">
<mapper namespace="com.chinasofti.mapper.UmessagesMapper">
  <resultMap id="BaseResultMap" type="com.chinasofti.pojo.Umessages">
    <!--
      WARNING - @mbg.generated
      This element is automatically generated by MyBatis Generator, do not modify.
      This element was generated on Tue Sep 24 12:52:39 CST 2019.
    -->
    <result column="tel" jdbcType="VARCHAR" property="tel" />
    <result column="wxid" jdbcType="VARCHAR" property="wxid" />
    <result column="gw" jdbcType="VARCHAR" property="gw" />
    <result column="kf" jdbcType="VARCHAR" property="kf" />
  </resultMap>
  <sql id="Example_Where_Clause">
    <!--
      WARNING - @mbg.generated
      This element is automatically generated by MyBatis Generator, do not modify.
      This element was generated on Tue Sep 24 12:52:39 CST 2019.
    -->
    <where>
      <foreach collection="oredCriteria" item="criteria" separator="or">
        <if test="criteria.valid">
          <trim prefix="(" prefixOverrides="and" suffix=")">
            <foreach collection="criteria.criteria" item="criterion">
              <choose>
                <when test="criterion.noValue">
                  and ${criterion.condition}
                </when>
                <when test="criterion.singleValue">
                  and ${criterion.condition} #{criterion.value}
                </when>
                <when test="criterion.betweenValue">
                  and ${criterion.condition} #{criterion.value} and #{criterion.secondValue}
                </when>
                <when test="criterion.listValue">
                  and ${criterion.condition}
                  <foreach close=")" collection="criterion.value" item="listItem" open="(" separator=",">
                    #{listItem}
                  </foreach>
                </when>
              </choose>
            </foreach>
          </trim>
        </if>
      </foreach>
    </where>
  </sql>
  <sql id="Update_By_Example_Where_Clause">
    <!--
      WARNING - @mbg.generated
      This element is automatically generated by MyBatis Generator, do not modify.
      This element was generated on Tue Sep 24 12:52:39 CST 2019.
    -->
    <where>
      <foreach collection="example.oredCriteria" item="criteria" separator="or">
        <if test="criteria.valid">
          <trim prefix="(" prefixOverrides="and" suffix=")">
            <foreach collection="criteria.criteria" item="criterion">
              <choose>
                <when test="criterion.noValue">
                  and ${criterion.condition}
                </when>
                <when test="criterion.singleValue">
                  and ${criterion.condition} #{criterion.value}
                </when>
                <when test="criterion.betweenValue">
                  and ${criterion.condition} #{criterion.value} and #{criterion.secondValue}
                </when>
                <when test="criterion.listValue">
                  and ${criterion.condition}
                  <foreach close=")" collection="criterion.value" item="listItem" open="(" separator=",">
                    #{listItem}
                  </foreach>
                </when>
              </choose>
            </foreach>
          </trim>
        </if>
      </foreach>
    </where>
  </sql>
  <sql id="Base_Column_List">
    <!--
      WARNING - @mbg.generated
      This element is automatically generated by MyBatis Generator, do not modify.
      This element was generated on Tue Sep 24 12:52:39 CST 2019.
    -->
    tel, wxid, gw, kf
  </sql>
  <select id="selectByExample" parameterType="com.chinasofti.pojo.UmessagesExample" resultMap="BaseResultMap">
    <!--
      WARNING - @mbg.generated
      This element is automatically generated by MyBatis Generator, do not modify.
      This element was generated on Tue Sep 24 12:52:39 CST 2019.
    -->
    select
    <if test="distinct">
      distinct
    </if>
    <include refid="Base_Column_List" />
    from umessages
    <if test="_parameter != null">
      <include refid="Example_Where_Clause" />
    </if>
    <if test="orderByClause != null">
      order by ${orderByClause}
    </if>
  </select>
  <delete id="deleteByExample" parameterType="com.chinasofti.pojo.UmessagesExample">
    <!--
      WARNING - @mbg.generated
      This element is automatically generated by MyBatis Generator, do not modify.
      This element was generated on Tue Sep 24 12:52:39 CST 2019.
    -->
    delete from umessages
    <if test="_parameter != null">
      <include refid="Example_Where_Clause" />
    </if>
  </delete>
  <insert id="insert" parameterType="com.chinasofti.pojo.Umessages">
    <!--
      WARNING - @mbg.generated
      This element is automatically generated by MyBatis Generator, do not modify.
      This element was generated on Tue Sep 24 12:52:39 CST 2019.
    -->
    insert into umessages (tel, wxid, gw, 
      kf)
    values (#{tel,jdbcType=VARCHAR}, #{wxid,jdbcType=VARCHAR}, #{gw,jdbcType=VARCHAR}, 
      #{kf,jdbcType=VARCHAR})
  </insert>
  <insert id="insertSelective" parameterType="com.chinasofti.pojo.Umessages">
    <!--
      WARNING - @mbg.generated
      This element is automatically generated by MyBatis Generator, do not modify.
      This element was generated on Tue Sep 24 12:52:39 CST 2019.
    -->
    insert into umessages
    <trim prefix="(" suffix=")" suffixOverrides=",">
      <if test="tel != null">
        tel,
      </if>
      <if test="wxid != null">
        wxid,
      </if>
      <if test="gw != null">
        gw,
      </if>
      <if test="kf != null">
        kf,
      </if>
    </trim>
    <trim prefix="values (" suffix=")" suffixOverrides=",">
      <if test="tel != null">
        #{tel,jdbcType=VARCHAR},
      </if>
      <if test="wxid != null">
        #{wxid,jdbcType=VARCHAR},
      </if>
      <if test="gw != null">
        #{gw,jdbcType=VARCHAR},
      </if>
      <if test="kf != null">
        #{kf,jdbcType=VARCHAR},
      </if>
    </trim>
  </insert>
  <select id="countByExample" parameterType="com.chinasofti.pojo.UmessagesExample" resultType="java.lang.Long">
    <!--
      WARNING - @mbg.generated
      This element is automatically generated by MyBatis Generator, do not modify.
      This element was generated on Tue Sep 24 12:52:39 CST 2019.
    -->
    select count(*) from umessages
    <if test="_parameter != null">
      <include refid="Example_Where_Clause" />
    </if>
  </select>
  <update id="updateByExampleSelective" parameterType="map">
    <!--
      WARNING - @mbg.generated
      This element is automatically generated by MyBatis Generator, do not modify.
      This element was generated on Tue Sep 24 12:52:39 CST 2019.
    -->
    update umessages
    <set>
      <if test="record.tel != null">
        tel = #{record.tel,jdbcType=VARCHAR},
      </if>
      <if test="record.wxid != null">
        wxid = #{record.wxid,jdbcType=VARCHAR},
      </if>
      <if test="record.gw != null">
        gw = #{record.gw,jdbcType=VARCHAR},
      </if>
      <if test="record.kf != null">
        kf = #{record.kf,jdbcType=VARCHAR},
      </if>
    </set>
    <if test="_parameter != null">
      <include refid="Update_By_Example_Where_Clause" />
    </if>
  </update>
  <update id="updateByExample" parameterType="map">
    <!--
      WARNING - @mbg.generated
      This element is automatically generated by MyBatis Generator, do not modify.
      This element was generated on Tue Sep 24 12:52:39 CST 2019.
    -->
    update umessages
    set tel = #{record.tel,jdbcType=VARCHAR},
      wxid = #{record.wxid,jdbcType=VARCHAR},
      gw = #{record.gw,jdbcType=VARCHAR},
      kf = #{record.kf,jdbcType=VARCHAR}
    <if test="_parameter != null">
      <include refid="Update_By_Example_Where_Clause" />
    </if>
  </update>
</mapper>